robist/__init__.py
robist/robist.py
robist-2024.2.0.dist-info/LICENSE.txt
robist-2024.2.0.dist-info/METADATA
robist-2024.2.0.dist-info/WHEEL
robist-2024.2.0.dist-info/top_level.txt
robist-2024.2.0.dist-info/RECORD
