Metadata-Version: 2.1
Name: robist
Version: 2024.2.0
Summary: Robust Optimization by Iterative Scenario Sampling and Statistical Testing
Author-email: Justin Starreveld <j.s.starreveld@uva.nl>, Guanyu Jin <g.jin@uva.nl>
License: MIT License
Project-URL: Repository, https://github.com/JustinStarreveld/ROBIST/
Requires-Python: >=3.7
License-File: LICENSE.txt
Requires-Dist: numpy
Requires-Dist: scipy
Requires-Dist: scikit-learn
Requires-Dist: matplotlib
Requires-Dist: cvxpy
Requires-Dist: pyprojroot
Provides-Extra: examples
Requires-Dist: pandas ; extra == 'examples'
